vasprun/__init__.py
vasprun/io.py
vasprun/plot.py
vasprun-0.1.0.data/scripts/vasprun
vasprun-0.1.0.dist-info/LICENSE
vasprun-0.1.0.dist-info/METADATA
vasprun-0.1.0.dist-info/WHEEL
vasprun-0.1.0.dist-info/top_level.txt
vasprun-0.1.0.dist-info/RECORD
