Metadata-Version: 2.1
Name: vasprun
Version: 0.1.0
Summary: Utility/library to process vasprun.xml, possibly more.
Home-page: https://github.com/smarkov/vasprun/
Author: Stanislav Markov
Author-email: UNKNOWN
License: UNKNOWN
Platform: platform independent
Classifier: Programming Language :: Python
Classifier: Environment :: Console
Classifier: Intended Audience :: Science/Research
Classifier: License :: OSI Approved :: MIT License
Classifier: Operating System :: OS Independent
Classifier: Topic :: Scientific/Engineering
Requires-Dist: numpy
Requires-Dist: ase
Requires-Dist: lxml
Requires-Dist: matplotlib
Requires-Dist: json-tricks
